qdyhgq_macmcp_musicpro/__init__.py
qdyhgq_macmcp_musicpro-0.1.0.dist-info/METADATA
qdyhgq_macmcp_musicpro-0.1.0.dist-info/WHEEL
qdyhgq_macmcp_musicpro-0.1.0.dist-info/entry_points.txt
qdyhgq_macmcp_musicpro-0.1.0.dist-info/RECORD
